aiohttp_babel/__init__.py
aiohttp_babel/locale.py
aiohttp_babel/middlewares.py
aiohttpbabel-0.0.7.dist-info/METADATA
aiohttpbabel-0.0.7.dist-info/WHEEL
aiohttpbabel-0.0.7.dist-info/top_level.txt
aiohttpbabel-0.0.7.dist-info/RECORD
