Metadata-Version: 2.1
Name: aiohttpbabel
Version: 0.0.7
Summary: Babel localisation support for aiohttp
Home-page: https://gitlab.com/nicofonk/aiohttp-babel
Author: zhouyang
Author-email: zhouyang@zhouyang.me
License: BSD
Keywords: aiohttp locale babel localisation
Platform: UNKNOWN
Classifier: Programming Language :: Python :: 3.7
Requires-Dist: aiohttp
Requires-Dist: babel
Requires-Dist: speaklater
